baseqRNA/__init__.py
baseqRNA/aligner.py
baseqRNA/cmd.py
baseqRNA/command.py
baseqRNA/config.py
baseqRNA/fastqfiles.py
baseqRNA/pipeline.py
baseqRNA/quantify.py
baseqRNA/salmon.py
baseqRNA/Cluster/__init__.py
baseqRNA/Cluster/scanpy.py
baseqRNA/Cluster/seurat.py
baseqRNA/QC/__init__.py
baseqRNA/QC/corrheatmap.py
baseqRNA/QC/exptable.py
baseqRNA/QC/markers.py
baseqRNA/QC/pca.py
baseqRNA/QC/precision.py
baseqRNA/QC/scatterplot.py
baseqRNA/Scanpy/__init__.py
baseqRNA/Scanpy/read.py
baseqRNA-1.5.dist-info/DESCRIPTION.rst
baseqRNA-1.5.dist-info/METADATA
baseqRNA-1.5.dist-info/RECORD
baseqRNA-1.5.dist-info/WHEEL
baseqRNA-1.5.dist-info/entry_points.txt
baseqRNA-1.5.dist-info/metadata.json
baseqRNA-1.5.dist-info/top_level.txt
