Metadata-Version: 2.0
Name: baseqRNA
Version: 1.5
Summary: Pipeline for Processing RNA-Seq datasets
Home-page: https://www.beiseq.com
Author: Xiannian Zhang
Author-email: friedpine@gmail.com
License: UNKNOWN
Keywords: sample setuptools development
Platform: UNKNOWN
Classifier: Development Status :: 3 - Alpha
Classifier: Intended Audience :: Developers
Classifier: Topic :: Software Development :: Build Tools
Classifier: License :: OSI Approved :: MIT License
Classifier: Programming Language :: Python :: 3.6
Requires-Dist: click
Requires-Dist: configparser
Requires-Dist: matplotlib
Requires-Dist: numpy
Requires-Dist: pandas
Provides-Extra: dev
Requires-Dist: check-manifest; extra == 'dev'
Provides-Extra: test
Requires-Dist: coverage; extra == 'test'
